Metadata-Version: 2.1
Name: VerySimpleCalculator
Version: 0.0.1
Summary: aVeryBasicCalculator
Home-page: UNKNOWN
Author: Felix Bartels
Author-email: felix.bartels97@gmail.com
License: MIT
Keywords: calculator
Platform: UNKNOWN
Classifier: Development Status :: 5 - Production/Stable
Classifier: Intended Audience :: Education
Classifier: Operating System :: Microsoft :: Windows :: Windows 10
Classifier: License :: OSI Approved :: MIT License
Classifier: Programming Language :: Python :: 3
License-File: LICENSE.txt
